easydi/__init__.py
easydi-0.2.1.dist-info/LICENSE
easydi-0.2.1.dist-info/METADATA
easydi-0.2.1.dist-info/WHEEL
easydi-0.2.1.dist-info/top_level.txt
easydi-0.2.1.dist-info/RECORD
