Metadata-Version: 2.1
Name: easydi
Version: 0.2.1
Summary: Lazy dependency injection
Home-page: https://github.com/wiryonolau/python-easydi
Author: Wiryono Lauw
Author-email: wiryonolau@gmail.com
License: gpl-2.0
Platform: UNKNOWN
Classifier: Programming Language :: Python :: 3
Classifier: Programming Language :: Python :: 3.4
Classifier: Programming Language :: Python :: 3.5
Classifier: Programming Language :: Python :: 3.6
Requires-Dist: readerwriterlock (==1.0.4)
